iptuapi/__init__.py
iptuapi/client.py
iptuapi/exceptions.py
iptuapi/models.py
iptuapi-2.1.0.dist-info/licenses/LICENSE
iptuapi-2.1.0.dist-info/METADATA
iptuapi-2.1.0.dist-info/WHEEL
iptuapi-2.1.0.dist-info/top_level.txt
iptuapi-2.1.0.dist-info/RECORD
