Metadata-Version: 2.4
Name: iptuapi
Version: 2.1.0
Summary: SDK oficial para a IPTU API - Dados de IPTU de São Paulo, Belo Horizonte e Recife
Author-email: IPTU API <contato@iptuapi.com.br>
License: Proprietary
Project-URL: Homepage, https://iptuapi.com.br
Project-URL: Documentation, https://iptuapi.com.br/docs
Project-URL: Repository, https://github.com/iptuapi/iptuapi-python
Project-URL: Changelog, https://github.com/iptuapi/iptuapi-python/blob/main/CHANGELOG.md
Project-URL: Issues, https://github.com/iptuapi/iptuapi-python/issues
Keywords: iptu,api,são paulo,belo horizonte,recife,imóveis,dados,real estate,property
Classifier: Development Status :: 5 - Production/Stable
Classifier: Intended Audience :: Developers
Classifier: License :: OSI Approved :: MIT License
Classifier: Operating System :: OS Independent
Classifier: Programming Language :: Python :: 3
Classifier: Programming Language :: Python :: 3.9
Classifier: Programming Language :: Python :: 3.10
Classifier: Programming Language :: Python :: 3.11
Classifier: Programming Language :: Python :: 3.12
Classifier: Programming Language :: Python :: 3.13
Classifier: Topic :: Software Development :: Libraries :: Python Modules
Classifier: Typing :: Typed
Requires-Python: >=3.9
License-File: LICENSE
Requires-Dist: requests>=2.28.0
Requires-Dist: pydantic>=2.0.0
Requires-Dist: urllib3>=2.0.0
Provides-Extra: dev
Requires-Dist: pytest>=7.0.0; extra == "dev"
Requires-Dist: pytest-cov>=4.0.0; extra == "dev"
Requires-Dist: pytest-mock>=3.10.0; extra == "dev"
Requires-Dist: responses>=0.23.0; extra == "dev"
Requires-Dist: mypy>=1.0.0; extra == "dev"
Requires-Dist: ruff>=0.1.0; extra == "dev"
Dynamic: license-file
